Workbook

Sheet 1. Govt Claim
A1: PAKISTAN POVERTY LINE — OFFICIAL GOVERNMENT CLAIM
A2: Economic Survey of Pakistan 2024-25 | Finance Minister Muhammad Aurangzeb
A4: Item | B4: Government Figure | C4: Notes / Source
A5: Monthly Poverty Line (PKR) | B5: 8483 | C5: Official — Economic Survey of Pakistan 2024-25
A6: Daily Poverty Line (PKR) | B6: =B5/30 -> 282.76667 | C6: At approx. 1 USD = 278 PKR
A7: Annual Poverty Line (PKR) | B7: =B5*12 -> 101796 | C7: Annualised figure
A8: USD equivalent / month | B8: =B5/278 -> 30.514388 | C8: At ~1 USD = 278 PKR
A9: Source | B9: Economic Survey of Pakistan 2024-25 | C9: Presented June 2025
A10: Status | B10: NATIONALLY APPLIED threshold | C10: Same figure applied to 240 million people across all provinces
A12: ⚠ This single threshold is applied nationally — it does not account for regional cost-of-living differences between Karachi, Lahore, Peshawar, rural Sindh, or Balochistan.

Sheet 2. Multi-City Expenses
A1: REAL MONTHLY SURVIVAL COST — PAKISTAN MULTI-CITY COMPARISON
A2: Single adult, minimum survival budget | Mid-2025 estimates
A4: Expense Category | B4: Karachi | C4: Lahore | D4: Islamabad/RWP | E4: Peshawar | F4: Interior Sindh (rural) | G4: Notes / Basis | H4: Source
A5: Food (basic groceries) | B5: 10000 | C5: 9000 | D5: 8500 | E5: 8000 | F5: 6500 | G5: Higher in Karachi/Lahore; rural Sindh lower but rising | H5: PBS HIES 2024-25 (Household Integrated Economic Survey), food & beverage category average
A6: Rent — basic single room | B6: 18000 | C6: 12000 | D6: 8000 | E6: 7000 | F6: 3000 | G6: Karachi: North Nazimabad/Landhi. Lahore: Samanabad. RWP: Satellite Town | H6: Zameen.com and OLX rental listings, mid-2025 sample (informal — not an official index)
A7: Electricity (summer peak) | B7: 6000 | C7: 5000 | D7: 3500 | E7: 2500 | F7: 4000 | G7: KESC/K-Electric (Karachi); LESCO (Lahore); IESCO (RWP); PESCO (KPK); HESCO/SEPCO (Sindh) | H7: IESCO / LESCO / K-Electric / PESCO / HESCO published tariff schedules, summer slab
A8: Gas / Fuel | B8: 1200 | C8: 1000 | D8: 600 | E8: 800 | F8: 1500 | G8: Interior Sindh: no piped gas — LPG cylinder ~Rs. 3,000+ per month | H8: OGRA LPG price notifications (interior Sindh) and SNGPL piped-gas tariff (other cities)
A9: Water | B9: 1000 | C9: 700 | D9: 500 | E9: 600 | F9: 800 | G9: KWSB (Karachi); WASA (Lahore/RWP); tanker supplements in all cities | H9: WASA (Lahore/RWP) and KWSB (Karachi) published water tariffs; informal for tanker top-ups
A10: Transport (daily commute) | B10: 4000 | C10: 3000 | D10: 2000 | E10: 2500 | F10: 1500 | G10: Karachi: bus/rickshaw; Lahore: Metro/rickshaw; RWP: Metro Bus; rural: motorbike fuel | H10: Local fare estimates — no single official source; verify against city transport authority rates
A11: Mobile / Internet (prepaid) | B11: 1200 | C11: 1000 | D11: 800 | E11: 800 | F11: 700 | G11: Jazz/Telenor prepaid bundle; connectivity lower in interior | H11: Jazz/Telenor publicly listed prepaid bundle prices
A12: Healthcare (basic OPD) | B12: 2000 | C12: 1500 | D12: 500 | E12: 800 | F12: 600 | G12: Private GP costs higher in Karachi; rural relies on Basic Health Units (often dysfunctional) | H12: Estimated from private GP consultation fee surveys — not an official source, verify locally
A13: Clothing / household (monthly share) | B13: 1500 | C13: 1200 | D13: 700 | E13: 800 | F13: 600 | G13: Amortised over year; basic seasonal clothing | H13: PBS HIES 2024-25 clothing/household category, amortised over the year
A14: Education (1 child, govt school fees/supplies) | B14: 1500 | C14: 1200 | D14: 1000 | E14: 800 | F14: 500 | G14: Optional — set 0 for single adult; significant for families | H14: Estimated from public-school fee/supply cost surveys; verify with provincial education dept.
A15: Emergency buffer (8%) | B15: =SUM(B5:B14)*0.08 -> 3712 | C15: =SUM(C5:C14)*0.08 -> 2848 | D15: =SUM(D5:D14)*0.08 -> 2088 | E15: =SUM(E5:E14)*0.08 -> 1968 | F15: =SUM(F5:F14)*0.08 -> 1576 | G15: 8% buffer for unplanned expenses | H15: Calculated (8% of subtotal) — not independently sourced
A16: TOTAL MINIMUM MONTHLY COST | B16: =SUM(B5:B15) -> 50112 | C16: =SUM(C5:C15) -> 38448 | D16: =SUM(D5:D15) -> 28188 | E16: =SUM(E5:E15) -> 26568 | F16: =SUM(F5:F15) -> 21276 | G16: Compare each city total vs govt poverty line of Rs. 8,483 | H16: Calculated (sum of rows above)
A18: ⚠ All figures are estimates for illustrative purposes. Sources: PBS HIES 2024-25 | K-Electric/LESCO/IESCO/PESCO/HESCO tariffs | KWSB/WASA/WAPDA | Zameen.com/OLX (rent) | local market prices. Interior Sindh uses LPG (no SNGPL grid). Verify all before publication.

Sheet 3. National Gap Analysis
A1: NATIONAL GAP ANALYSIS — Rs. 8,483 Poverty Line vs. Real Survival Cost
A2: How disconnected is the official figure from reality — city by city?
A4: Metric | B4: Karachi | C4: Lahore | D4: Islamabad/RWP | E4: Peshawar | F4: Interior Sindh (rural) | G4: Interpretation
A5: Govt Poverty Line (PKR) | B5: 8483 | C5: 8483 | D5: 8483 | E5: 8483 | F5: 8483 | G5: Same threshold applied nationally
A6: Estimated Min Monthly Cost (PKR) | B6: ='2. Multi-City Expenses'!B16 -> 50112 | C6: ='2. Multi-City Expenses'!C16 -> 38448 | D6: ='2. Multi-City Expenses'!D16 -> 28188 | E6: ='2. Multi-City Expenses'!E16 -> 26568 | F6: ='2. Multi-City Expenses'!F16 -> 21276 | G6: Linked from Sheet 2 totals
A7: Monthly Shortfall (PKR) | B7: =B6-B5 -> 41629 | C7: =C6-C5 -> 29965 | D7: =D6-D5 -> 19705 | E7: =E6-E5 -> 18085 | F7: =F6-F5 -> 12793 | G7: Positive = real cost exceeds poverty line
A8: Shortfall as % above poverty line | B8: =(B6-B5)/B5 -> 4.9073441 | C8: =(C6-C5)/C5 -> 3.5323588 | D8: =(D6-D5)/D5 -> 2.3228811 | E8: =(E6-E5)/E5 -> 2.1319109 | F8: =(F6-F5)/F5 -> 1.508075 | G8: How many % above the line is the real minimum?
A9: Poverty line covers only this % of real cost | B9: =B5/B6 -> 0.16928081 | C9: =C5/C6 -> 0.22063566 | D9: =D5/D6 -> 0.30094366 | E9: =E5/E6 -> 0.31929389 | F9: =F5/F6 -> 0.39871216 | G9: Lower = more disconnected from reality
A10: Months a poverty-line earner can survive | B10: =B5/B6*12 -> 2.0313697 | C10: =C5/C6*12 -> 2.647628 | D10: =D5/D6*12 -> 3.611324 | E10: =E5/E6*12 -> 3.8315266 | F10: =F5/F6*12 -> 4.784546 | G10: Out of 12 months — how many does Rs. 8,483 cover?
A12: KEY FINDING: A nationally uniform poverty threshold of Rs. 8,483 is absurd in Karachi where rent alone exceeds it. It is equally misleading in rural Sindh where cash income is irregular and LPG/transport costs are disproportionately high.

Sheet 4. Elite Context (Unverified)
A1: COMMENTARY — ELITE PRIVILEGES vs. POVERTY LINE (UNVERIFIED ESTIMATES)
A2: Illustrative only — most figures below have no traceable official source. Do not present as audited data.
A4: Item | B4: Estimated Cost (PKR) | C4: Months of 'Poverty Line' Income | D4: Notes / Source | E4: Confidence
A5: Govt poverty line (1 month) | B5: 8483 | C5: =B5/8483 -> 1 | D5: The official 'not poor' threshold | E5: Official — Economic Survey of Pakistan 2024-25
A6: PIA Business Class ticket (domestic, 1 way) | B6: 65000 | C6: =B6/8483 -> 7.6623836 | D6: Approx. Karachi–Islamabad business class; verify on PIA.com | E6: Verifiable — check current published fares on PIA.com
A7: Federal minister daily TA/DA allowance (est.) | B7: 25000 | C7: =B7/8483 -> 2.9470706 | D7: Approximate — actual figures vary; verify from Finance Division notifications | E7: Unverified — no public source found; author estimate
A8: Government officer protocol car fuel (monthly est.) | B8: 40000 | C8: =B8/8483 -> 4.715313 | D8: Estimate based on fuel allowance norms; verify from Establishment Division | E8: Unverified — no public source found; author estimate
A9: One diplomatic dinner / state function (per head est.) | B9: 15000 | C9: =B9/8483 -> 1.7682424 | D9: Approximate based on reported costs; verify from PAC/AGPR reports | E9: Unverified — no public source found; author estimate
A10: MNA/MPA monthly salary + allowances (approx.) | B10: 250000 | C10: =B10/8483 -> 29.470706 | D10: Includes salary, constituency allowance, fuel, medical; verify from NA website | E10: Partially verifiable — NA website publishes salary/allowance structure, not a single total
A11: PM/CM motorcade operational cost per trip (est.) | B11: 500000 | C11: =B11/8483 -> 58.941412 | D11: Multiple protocol vehicles, security, fuel; estimate only — no official disclosure | E11: Unverified — no official disclosure exists for this figure
A12: Annual cost of one Grade-22 officer perks (est.) | B12: 2400000 | C12: =B12/8483 -> 282.91878 | D12: Housing, car, fuel, medical, servants — divided by 12 for monthly; estimate only | E12: Unverified — no public source found; author estimate
A13: Annual elite residential enclave subsidy (utilities — est.) | B13: 1200000 | C13: =B13/8483 -> 141.45939 | D13: Below-market utility rates for DHA/Cantonment residents — estimate; verify from utility companies | E13: Unverified — no public source found; author estimate
A15: READING THIS SHEET: Column C shows how many months of the official 'poverty line income' equals the cost of each single item. A PM motorcade trip = ~59 months of poverty-line income.
A17: ⚠ IMPORTANT: All 'elite perk' figures are ESTIMATES compiled from published reports, media investigations, and PAC proceedings. They are approximations, not audited figures. Mark clearly as 'estimated' in any public use. Recommended verification: Finance Division, Establishment Division, National Assembly website, AGPR annual reports.

Sheet 5. Dashboard
B1: THE Rs. 8,483 QUESTION — NATIONAL PICTURE
B2: Pakistan Poverty Line vs. Real Survival Cost — City by City | 2025
B4: Karachi | C4: Lahore | D4: Islamabad/RWP | E4: Peshawar | F4: Interior Sindh
B5: ='2. Multi-City Expenses'!B16 -> 50112 | C5: ='2. Multi-City Expenses'!C16 -> 38448 | D5: ='2. Multi-City Expenses'!D16 -> 28188 | E5: ='2. Multi-City Expenses'!E16 -> 26568 | F5: ='2. Multi-City Expenses'!F16 -> 21276
B6: ='3. National Gap Analysis'!B7 -> 41629 | C6: ='3. National Gap Analysis'!C7 -> 29965 | D6: ='3. National Gap Analysis'!D7 -> 19705 | E6: ='3. National Gap Analysis'!E7 -> 18085 | F6: ='3. National Gap Analysis'!F7 -> 12793
B7: ↑ monthly shortfall | C7: ↑ monthly shortfall | D7: ↑ monthly shortfall | E7: ↑ monthly shortfall | F7: ↑ monthly shortfall
B9: City | C9: Real Min Cost | D9: Govt Poverty Line
B10: Karachi | C10: ='2. Multi-City Expenses'!B16 -> 50112 | D10: 8483
B11: Lahore | C11: ='2. Multi-City Expenses'!C16 -> 38448 | D11: 8483
B12: Isb/RWP | C12: ='2. Multi-City Expenses'!D16 -> 28188 | D12: 8483
B13: Peshawar | C13: ='2. Multi-City Expenses'!E16 -> 26568 | D13: 8483
B14: Int. Sindh | C14: ='2. Multi-City Expenses'!F16 -> 21276 | D14: 8483
B47: ⚠ All figures estimated. Red bars = Rs. 8,483 poverty line. Verify against PBS HIES 2024-25 | Utility company tariffs | Zameen.com | Economic Survey 2024-25.
